LICENSE
MANIFEST.in
README.md
requirements.txt
setup.py
texmex_python/__init__.py
texmex_python/reader.py
texmex_python/writer.py
texmex_python.egg-info/PKG-INFO
texmex_python.egg-info/SOURCES.txt
texmex_python.egg-info/dependency_links.txt
texmex_python.egg-info/not-zip-safe
texmex_python.egg-info/requires.txt
texmex_python.egg-info/top_level.txt