Metadata-Version: 1.0
Name: texmex-python
Version: 1.0.0
Summary: read texmex dataset
Home-page: https://github.com/Hi-king/read_texmex_dataset_python
Author: Hi-king
Author-email: hikingko1@gmail.com
License: UNKNOWN
Platform: UNKNOWN
